terrasafe/__init__.py
terrasafe/terrasafe.py
terrasafe-0.5.1.dist-info/METADATA
terrasafe-0.5.1.dist-info/WHEEL
terrasafe-0.5.1.dist-info/entry_points.txt
terrasafe-0.5.1.dist-info/top_level.txt
terrasafe-0.5.1.dist-info/RECORD
