Metadata-Version: 2.1
Name: terrasafe
Version: 0.5.1
Summary: A CLI tool to analyze Terraform plan files, and prevent unallowed resources deletions and drop/create actions.
Home-page: https://github.com/PrismeaOpsTeam/Terrasafe
Author: PrismeaOpsTeam
Author-email: team-ops@prismea.fr
License: GPLv3
Platform: UNKNOWN
Classifier: Programming Language :: Python :: 3
Classifier: Operating System :: OS Independent
Requires-Python: >=3.6
